pyliferisk/__init__.py
pyliferisk/mortalitytables.py
pyliferisk-1.12.0.dist-info/LICENSE
pyliferisk-1.12.0.dist-info/METADATA
pyliferisk-1.12.0.dist-info/WHEEL
pyliferisk-1.12.0.dist-info/top_level.txt
pyliferisk-1.12.0.dist-info/RECORD
