Metadata-Version: 2.1
Name: pyliferisk
Version: 1.12.0
Summary: A python library for life actuarial calculations, simple, powerful and easy-to-use
Home-page: https://github.com/franciscogarate/pyliferisk
Author: Francisco Garate
Author-email: fgaratesantiago@gmail.com
Classifier: License :: OSI Approved :: GNU General Public License v3 (GPLv3)
Classifier: Operating System :: OS Independent
Classifier: Programming Language :: Python :: 2.7
Classifier: Programming Language :: Python :: 3
Classifier: Topic :: Scientific/Engineering :: Mathematics
Classifier: Intended Audience :: Financial and Insurance Industry
License-File: LICENSE
